README.rst
setup.py
wishbone_input_gearman/__init__.py
wishbone_input_gearman/gearmanin.py
wishbone_input_gearman.egg-info/PKG-INFO
wishbone_input_gearman.egg-info/SOURCES.txt
wishbone_input_gearman.egg-info/dependency_links.txt
wishbone_input_gearman.egg-info/entry_points.txt
wishbone_input_gearman.egg-info/namespace_packages.txt
wishbone_input_gearman.egg-info/not-zip-safe
wishbone_input_gearman.egg-info/requires.txt
wishbone_input_gearman.egg-info/top_level.txt